[
  {
    "page": 1,
    "day": 1,
    "start_period": 1,
    "end_period": 2,
    "weeks": "9-16周",
    "name": "优化导论实验",
    "location": "电子楼418A",
    "teacher": "郑立刚",
    "raw": "(1-2节)9-16周/校区:大学城场地:电子楼418A/教师:郑立刚/教学班:(2025-2026-2)180600107-01/教学班组成:计科232;计科233;计科（创）231/考核方式:考查选课备注:无/课程学时组成:实验:16/周学时:2/总学时:16/学分:0.5计算机视觉与模式识别*"
  },
  {
    "page": 1,
    "day": 1,
    "start_period": 1,
    "end_period": 2,
    "weeks": "5-8周",
    "name": "自然语言处理",
    "location": "电子楼416A",
    "teacher": "杨朔",
    "raw": "(1-2节)5-8周/校区:大学城场地:电子楼416A/教师:杨朔/教学班:(2025-2026-2)180600065-01A/教学班组成:计科232;计科233;计科（创）231/考核方式:未安排/选课备注:无/课程学时组成:理论:24,实验:8/周学时:2/总学时:8/学分:2.0优化导论实验&"
  },
  {
    "page": 1,
    "day": 1,
    "start_period": 3,
    "end_period": 4,
    "weeks": "1-16周",
    "name": "计算机视觉与模式识别",
    "location": "文新205",
    "teacher": "谢延昭",
    "raw": "(3-4节)1-16周/校区:大学城场地:文新205/教师:谢延昭教学班:(2025-2026-2)-210610004-02/教学班组成:计科233/考核方式:考试/选课备注:无/课程学时组成:理论:32/周学时:2/总学时:32/学分"
  },
  {
    "page": 2,
    "day": 1,
    "start_period": 5,
    "end_period": 6,
    "weeks": "9-16周",
    "name": "计算机视觉与模式识别实验",
    "location": "电子楼513",
    "teacher": "谢延昭",
    "raw": "(5-6节)9-16周/校区:大学城场地:电子楼513/教师:谢延昭/教学班:(2025-2026-2)210610005-03/教学班组成:计科233/考核方式:考查/选课备注:无/课程学时组成:实验:16/周学时:2/总学时:16/学分:0.5自然语言处理*"
  },
  {
    "page": 2,
    "day": 1,
    "start_period": 6,
    "end_period": 8,
    "weeks": "1-8周",
    "name": "自然语言处理",
    "location": "文渊406",
    "teacher": "杨朔",
    "raw": "(6-8节)1-8周/校区:大学城场地:文渊406/教师:杨朔/教学班:(2025-2026-2)-180600065-01/教学班组成:计科232;计科233;计科（创）231/考核方式:考查选课备注:无/课程学时组成:理论:24,实验:8/周学时:2/总学时:24/学分:2.0"
  },
  {
    "page": 1,
    "day": 2,
    "start_period": 1,
    "end_period": 2,
    "weeks": "1-16周",
    "name": "物联网技术",
    "location": "文新205",
    "teacher": "唐琳",
    "raw": "(1-2节)1-16周/校区:大学城场地:文新205/教师:唐琳教学班:(2025-2026-2)-230600098-01/教学班组成:计科232;计科233;计科（创）231;网络232;网络（创）231/考核方式:考查/选课备注:无/课程学时组成:理论:32,实验:32/周学时:2/总学时:32/学分:3.0云平台与大数据*"
  },
  {
    "page": 1,
    "day": 2,
    "start_period": 3,
    "end_period": 4,
    "weeks": "13-16周",
    "name": "云平台与大数据",
    "location": "文渊306",
    "teacher": "王健雄",
    "raw": "(3-4节)13-16周/校区:大学城场地:文渊306/教师:王健雄教学班:(2025-2026-2)-210600036-03/教学班组成:计科233/考核方式:考查/选课备注:无/课程学时组成:理论"
  },
  {
    "page": 2,
    "day": 2,
    "start_period": 5,
    "end_period": 6,
    "weeks": "8周,14周",
    "name": "大学生心理健康教育实践课",
    "location": "理科南306（活）",
    "teacher": "谭庭松",
    "raw": "(5-6节)8周,14周/校区:大学城/场地:理科南306（活）教师:谭庭松/教学班:(2025-2026-2)-233800801-86/教学班组成:计科233/考核方式:考查/选课备注:无课程学时组成:实践:16/周学时:2/总学时:4/学分:1.0大学生心理健康教育实践课@"
  },
  {
    "page": 2,
    "day": 2,
    "start_period": 7,
    "end_period": 8,
    "weeks": "12周",
    "name": "大学生心理健康教育实践课",
    "location": "文新315（活）",
    "teacher": "谢灿杰",
    "raw": "(7-8节)12周/校区:大学城场地:文新315（活）/教师:谢灿杰/教学班:(2025-2026-2)233800801a-0624/教学班组成:无/考核方式:未安排/选课备注:无/课程学时组成:实践:4/周学时:2/总学时:2/学分:0"
  },
  {
    "page": 3,
    "day": 3,
    "start_period": 9,
    "end_period": 10,
    "weeks": "1-16周",
    "name": "优化导论",
    "location": "理科南214",
    "teacher": "郑立刚",
    "raw": "(9-10节)1-16周/校区:大学城场地:理科南214/教师:郑立刚/教学班:(2025-2026-2)180600106-01/教学班组成:计科232;计科233;计科（创）231/考核方式:考查选课备注:无/课程学时组成:理论:32/周学时:2/总学时:32/学分:2"
  },
  {
    "page": 2,
    "day": 4,
    "start_period": 7,
    "end_period": 8,
    "weeks": "9-16周",
    "name": "云平台与大数据",
    "location": "电子楼416A",
    "teacher": "王健雄",
    "raw": "(7-8节)9-16周/校区:大学城场地:电子楼416A/教师:王"
  },
  {
    "page": 2,
    "day": 4,
    "start_period": 7,
    "end_period": 8,
    "weeks": "5-8周",
    "name": "大学生职业发展与就业指导2",
    "location": "文渊305（阶）",
    "teacher": "唐蕾",
    "raw": "(7-8节)5-8周/校区:大学城场地:文渊305（阶）/教师:唐蕾/教学班:(2025-2026-2)185600802-78/教学班组成:计科232;计科233/考核方式:考查/选课备注:无/课程学时组成:理论:8/周学时:8总学时:8/学分:0.5云平台与大数据&"
  },
  {
    "page": 1,
    "day": 5,
    "start_period": 1,
    "end_period": 2,
    "weeks": "1-16周",
    "name": "物联网技术",
    "location": "电子楼412B",
    "teacher": "唐琳",
    "raw": "(1-2节)1-16周/校区:大学城场地:电子楼412B/教师:唐琳教学班:(2025-2026-2)-230600098-01A/教学班组成:计科232;计科233;计科（创）231;网络232;网络（创）231/考核方式:未安排/选课备注:无/课程学时组成:理论:32,实验:32/周学时:2/总学时:32/学分:3.0"
  },
  {
    "page": 2,
    "day": 5,
    "start_period": 5,
    "end_period": 7,
    "weeks": "1-8周",
    "name": "云平台与大数据",
    "location": "文渊306",
    "teacher": "王健雄",
    "raw": "(5-7节)1-8周/校区:大学城场地:文渊306/教师:王健雄教学班:(2025-2026-2)-210600036-03/教学班组成:计科233/考核方式:考查/选课备注:无/课程学时组成:理论:32,实验:16/周学时:2/总学时:32/学分:2.5"
  }
]